querycraft/Database.py
querycraft/LLM.py
querycraft/LRS.py
querycraft/SQL.py
querycraft/SQLException.py
querycraft/WindowDisplay.py
querycraft/__init__.py
querycraft/sqlsbs.py
querycraft/tools.py
querycraft/cache/explain_lms_mistralai_mistral-nemo-instruct-2407.json
querycraft/cache/readme.txt
querycraft/cache/solution_lms_mistralai_mistral-nemo-instruct-2407.json
querycraft/cache/solution_poe_gpt-5-nano.json
querycraft/config/config-sbs-save.cfg
querycraft/config/config-sbs.cfg
querycraft/cookies/emmanuel.desmontils@univ-nantes.fr.json
querycraft/cookies/readme.txt
querycraft/data/cours.db
querycraft/data/em.db
querycraft/data/librairie.db
querycraft/exos/ex1.json
querycraft/exos/exos1.json
querycraft/exos/readme.txt
querycraft/templates/correction_prompt-old.md
querycraft/templates/correction_prompt.md
querycraft/templates/database_prompt.md
querycraft/templates/erreur2_prompt.md
querycraft/templates/erreur_prompt.md
querycraft/templates/requete_prompt.md
querycraft/templates/systeme_prompt.md
querycraft-0.0.84.dist-info/licenses/AUTHORS
querycraft-0.0.84.dist-info/licenses/LICENSE
querycraft-0.0.84.dist-info/METADATA
querycraft-0.0.84.dist-info/WHEEL
querycraft-0.0.84.dist-info/entry_points.txt
querycraft-0.0.84.dist-info/top_level.txt
querycraft-0.0.84.dist-info/RECORD
