Metadata-Version: 2.4
Name: querycraft
Version: 0.0.84
Summary: Provide usefully SQL classes and functions to execute SQL queries step by step
Home-page: https://gitlab.univ-nantes.fr/ls2n-didactique/querycraft
Author: Emmanuel Desmontils
Author-email: emmanuel.desmontils@univ-nantes.fr
Maintainer: Emmanuel Desmontils
Maintainer-email:  emmanuel.desmontils@univ-nantes.fr
License: GPL V3
Keywords: SQL Step-By-Step Query Database
Platform: ALL
Classifier: Topic :: Education
Classifier: Programming Language :: Python :: 3
Classifier: Operating System :: OS Independent
Requires-Python: >=3.11.0
License-File: LICENSE
License-File: AUTHORS
Requires-Dist: argparse>=1.4.0
Requires-Dist: openai>=2.9.0
Requires-Dist: tincan>=1.0.0
Requires-Dist: mysql-connector-python>=9.0.0
Requires-Dist: lmstudio>=1.5.0
Requires-Dist: ollama>=0.4.7
Requires-Dist: keyboard>=0.13.5
Requires-Dist: google-genai>=1.61.0
Requires-Dist: sqlglot==25.33.0
Requires-Dist: colorama>=0.4.6
Dynamic: author
Dynamic: author-email
Dynamic: classifier
Dynamic: description
Dynamic: description-content-type
Dynamic: home-page
Dynamic: keywords
Dynamic: license
Dynamic: license-file
Dynamic: maintainer
Dynamic: maintainer-email
Dynamic: platform
Dynamic: requires-dist
Dynamic: requires-python
Dynamic: summary
